LICENSE.txt
MANIFEST.in
README.rst
requirements.txt
setup.py
docs/getting_started.rst
docs/index.rst
docs/module.rst
docs/tutorial.rst
sheetsync/__init__.py
sheetsync/version.py
sheetsync2.egg-info/PKG-INFO
sheetsync2.egg-info/SOURCES.txt
sheetsync2.egg-info/dependency_links.txt
sheetsync2.egg-info/requires.txt
sheetsync2.egg-info/top_level.txt