Metadata-Version: 1.1
Name: sheetsync2
Version: 0.2.5
Summary: Synchronize rows of data with a google spreadsheet (Python2.7 version)
Home-page: https://github.com/mbrenig/SheetSync/
Author: Mark Brenig-Jones
Author-email: markbrenigjones@gmail.com
License: UNKNOWN
Platform: any
Classifier: Development Status :: 4 - Beta
Classifier: License :: OSI Approved :: MIT License
Classifier: Programming Language :: Python :: 2.7
